vcrypto/__init__.py
vcrypto/encryption.py
vcrypto/secrets_manager.py
vcrypto/vcrypto.py
vcrypto-4.2.1.dist-info/METADATA
vcrypto-4.2.1.dist-info/WHEEL
vcrypto-4.2.1.dist-info/top_level.txt
vcrypto-4.2.1.dist-info/RECORD
