Metadata-Version: 2.2
Name: vcrypto
Version: 4.2.1
Summary: Utility to easily store passwords/secrets
Author-email: Arnau Villoro <arnau@villoro.com>
Maintainer-email: Arnau Villoro <arnau@villoro.com>
License: MIT
Classifier: Development Status :: 4 - Beta
Classifier: Intended Audience :: Developers
Classifier: Topic :: Security
Classifier: Topic :: Utilities
Classifier: License :: OSI Approved :: MIT License
Classifier: Programming Language :: Python
Classifier: Programming Language :: Python :: 3
Classifier: Programming Language :: Python :: 3.8
Classifier: Programming Language :: Python :: 3.9
Classifier: Programming Language :: Python :: 3.10
Classifier: Programming Language :: Python :: 3.11
Classifier: Programming Language :: Python :: 3.12
Requires-Python: >=3.8
Requires-Dist: cryptography>=44.0.1
Requires-Dist: loguru>=0.7.3
Requires-Dist: pytest>=8.3.4
Requires-Dist: pyyaml>=6.0.2
Requires-Dist: ruff>=0.9.7
